{
    "version": 1,
    "license": null,
    "copyright": null,
    "size": {
        "x": 32,
        "y": 32
    },
    "states": [
        {
            "name": "dread_ipad",
            "delays": [
                [
                    0.1,
                    0.1,
                    0.1,
                    0.1,
                    0.1,
                    0.1,
                    0.1,
                    0.1,
                    0.1,
                    0.1,
                    0.1,
                    0.1,
                    0.1,
                    0.1,
                    0.1
                ]
            ]
        },
        {
            "name": "overlay_template"
        },
        {
            "name": "judicial"
        },
        {
            "name": "vanguard"
        },
        {
            "name": "compromise"
        },
        {
            "name": "geis"
        },
        {
            "name": "volt"
        },
        {
            "name": "hateful_manacles"
        },
        {
            "name": "belligerent_eye",
            "delays": [
                [
                    0.1,
                    0.1,
                    0.1,
                    0.1
                ]
            ]
        },
        {
            "name": "vanguard_cogwheel",
            "delays": [
                [
                    2,
                    0.1,
                    0.1,
                    0.1,
                    0.1,
                    0.1,
                    0.1,
                    0.1,
                    0.1,
                    0.1
                ]
            ]
        },
        {
            "name": "geis_capacitor",
            "delays": [
                [
                    2,
                    0.1,
                    0.1,
                    0.1,
                    0.1,
                    0.1,
                    0.1,
                    0.1,
                    0.1,
                    0.1,
                    0.1,
                    0.1,
                    0.1,
                    0.1,
                    0.1,
                    0.1,
                    0.1,
                    0.1
                ]
            ]
        },
        {
            "name": "replicant_alloy",
            "delays": [
                [
                    2.5,
                    0.1,
                    0.030000001,
                    2,
                    0.07,
                    0.1,
                    0.1,
                    0.1,
                    0.1,
                    0.1,
                    0.1,
                    0.1,
                    0.1,
                    0.1,
                    0.1,
                    0.1,
                    0.1
                ]
            ]
        },
        {
            "name": "hierophant_ansible",
            "delays": [
                [
                    2,
                    0.1,
                    0.1,
                    1,
                    0.1,
                    0.1,
                    0.1,
                    0.1,
                    0.1,
                    2,
                    0.1,
                    0.1,
                    0.1
                ]
            ]
        },
        {
            "name": "judicial_visor_0"
        },
        {
            "name": "judicial_visor_1"
        },
        {
            "name": "truesight_lens"
        },
        {
            "name": "wraith_specs"
        },
        {
            "name": "soul_vessel"
        },
        {
            "name": "soul_vessel-searching",
            "delays": [
                [
                    0.1,
                    0.089999996,
                    0.089999996,
                    0.2,
                    0.089999996,
                    0.1,
                    0.089999996,
                    0.089999996,
                    0.089999996,
                    0.4,
                    0.089999996,
                    0.089999996,
                    0.089999996,
                    0.089999996,
                    0.5,
                    0.089999996,
                    0.089999996,
                    0.089999996,
                    0.089999996,
                    0.2,
                    0.089999996,
                    0.089999996,
                    0.089999996,
                    0.15,
                    0.089999996,
                    0.089999996,
                    0.089999996,
                    0.089999996,
                    0.1,
                    0.089999996
                ]
            ]
        },
        {
            "name": "soul_vessel-occupied",
            "delays": [
                [
                    0.089999996,
                    0.089999996,
                    0.089999996,
                    0.089999996,
                    0.089999996,
                    0.089999996,
                    0.089999996,
                    0.089999996,
                    0.089999996,
                    0.089999996,
                    0.089999996,
                    0.089999996,
                    0.089999996,
                    0.089999996,
                    0.089999996,
                    0.089999996,
                    0.089999996,
                    0.089999996,
                    0.089999996,
                    0.089999996,
                    0.089999996,
                    0.089999996,
                    0.089999996,
                    0.089999996,
                    0.089999996,
                    0.089999996,
                    0.089999996,
                    0.089999996,
                    0.089999996,
                    0.089999996
                ]
            ]
        },
        {
            "name": "replica_fabricator",
            "delays": [
                [
                    0.1,
                    0.1,
                    0.1
                ]
            ]
        },
        {
            "name": "ratvarian_spear"
        },
        {
            "name": "brass_filaments"
        },
        {
            "name": "ocular_warden",
            "directions": 4,
            "delays": [
                [
                    0.5,
                    0.5
                ],
                [
                    0.5,
                    0.5
                ],
                [
                    0.5,
                    0.5
                ],
                [
                    0.5,
                    0.5
                ]
            ]
        },
        {
            "name": "ocular_warden_unwrenched",
            "directions": 4,
            "delays": [
                [
                    1,
                    1
                ],
                [
                    1,
                    1
                ],
                [
                    1,
                    1
                ],
                [
                    1,
                    1
                ]
            ]
        },
        {
            "name": "blind_eye"
        },
        {
            "name": "gear_base"
        },
        {
            "name": "tinkerers_cache",
            "delays": [
                [
                    0.120000005,
                    0.120000005,
                    0.120000005,
                    0.120000005,
                    0.120000005,
                    0.120000005,
                    0.120000005,
                    0.120000005
                ]
            ]
        },
        {
            "name": "tinkerers_cache_unwrenched"
        },
        {
            "name": "interdiction_lens_inactive"
        },
        {
            "name": "interdiction_lens",
            "delays": [
                [
                    0.05,
                    0.05,
                    0.05,
                    0.05,
                    0.05,
                    0.05,
                    0.05,
                    0.05,
                    0.05,
                    0.05,
                    0.05
                ]
            ]
        },
        {
            "name": "interdiction_lens_recharged",
            "delays": [
                [
                    0.05,
                    0.05,
                    0.05,
                    0.05,
                    0.05,
                    0.05,
                    0.05,
                    0.05,
                    0.05
                ]
            ]
        },
        {
            "name": "interdiction_lens_active",
            "delays": [
                [
                    0.05,
                    0.05,
                    0.05,
                    0.05
                ]
            ]
        },
        {
            "name": "interdiction_lens_discharged",
            "delays": [
                [
                    0.05,
                    0.05,
                    0.05,
                    0.05,
                    0.05,
                    0.05,
                    0.05,
                    0.05,
                    0.05,
                    0.05
                ]
            ]
        },
        {
            "name": "interdiction_lens_unwrenched"
        },
        {
            "name": "lens_gem"
        },
        {
            "name": "prolonging_prism",
            "delays": [
                [
                    2,
                    0.120000005,
                    0.089999996,
                    0.089999996,
                    0.089999996,
                    0.089999996,
                    0.089999996,
                    0.089999996,
                    0.089999996,
                    0.089999996,
                    0.089999996,
                    0.089999996,
                    0.089999996,
                    0.089999996,
                    0.089999996,
                    0.089999996,
                    0.089999996,
                    0.089999996,
                    0.089999996,
                    0.089999996,
                    0.089999996,
                    0.089999996,
                    0.089999996,
                    0.089999996,
                    0.089999996,
                    0.089999996,
                    0.089999996,
                    0.089999996,
                    0.089999996,
                    0.089999996,
                    0.089999996,
                    0.089999996
                ]
            ]
        },
        {
            "name": "prolonging_prism_inactive"
        },
        {
            "name": "prolonging_prism_unwrenched"
        },
        {
            "name": "onyx_prism",
            "delays": [
                [
                    2.5,
                    0.1,
                    0.2,
                    0.3,
                    0.2,
                    0.1,
                    2.5
                ]
            ]
        },
        {
            "name": "mania_motor",
            "delays": [
                [
                    0.5,
                    0.065,
                    0.065,
                    0.065,
                    0.065,
                    0.065,
                    0.065,
                    0.065,
                    0.065,
                    0.065,
                    0.065,
                    0.065,
                    0.065,
                    0.065,
                    0.065,
                    0.08,
                    0.1,
                    0.1,
                    0.1,
                    0.1
                ]
            ]
        },
        {
            "name": "mania_motor_inactive"
        },
        {
            "name": "mania_motor_unwrenched"
        },
        {
            "name": "mania_motor_antennae",
            "delays": [
                [
                    2,
                    0.1,
                    0.1,
                    0.1,
                    2,
                    0.1,
                    0.1,
                    0.1
                ]
            ]
        },
        {
            "name": "tinkerers_daemon"
        },
        {
            "name": "tinkerers_daemon_unwrenched"
        },
        {
            "name": "replication_plate"
        },
        {
            "name": "t_belligerent_eye",
            "delays": [
                [
                    0.1,
                    0.1,
                    0.1
                ]
            ]
        },
        {
            "name": "t_vanguard_cogwheel",
            "delays": [
                [
                    0.1,
                    0.1,
                    0.1
                ]
            ]
        },
        {
            "name": "t_geis_capacitor",
            "delays": [
                [
                    0.1,
                    0.1,
                    0.1
                ]
            ]
        },
        {
            "name": "t_replicant_alloy",
            "delays": [
                [
                    0.1,
                    0.1,
                    0.1
                ]
            ]
        },
        {
            "name": "t_hierophant_ansible",
            "delays": [
                [
                    0.1,
                    0.1,
                    0.1
                ]
            ]
        },
        {
            "name": "t_random_component",
            "delays": [
                [
                    0.1,
                    0.1,
                    0.1,
                    0.1,
                    0.1,
                    0.1,
                    0.1,
                    0.1,
                    0.1,
                    0.1,
                    0.1,
                    0.1,
                    0.1,
                    0.1,
                    0.1
                ]
            ]
        },
        {
            "name": "tinkerglow",
            "delays": [
                [
                    0.1,
                    0.1,
                    0.1,
                    0.1,
                    0.1,
                    0.1,
                    0.1,
                    0.1,
                    0.1,
                    0.1,
                    0.1,
                    0.1,
                    0.1,
                    0.1,
                    0.1,
                    0.1,
                    0.1,
                    0.1,
                    0.1,
                    0.1,
                    0.1,
                    0.1,
                    0.1
                ]
            ]
        },
        {
            "name": "obelisk",
            "delays": [
                [
                    0.6,
                    0.6,
                    0.6,
                    0.6,
                    0.6,
                    0.6,
                    0.6,
                    0.6,
                    0.6,
                    0.6,
                    0.6,
                    0.2,
                    0.2,
                    0.2,
                    0.2,
                    0.2,
                    0.2,
                    0.2,
                    0.2,
                    0.2,
                    0.2,
                    0.2,
                    0.2,
                    0.2,
                    0.2,
                    0.2,
                    0.2,
                    0.2,
                    0.2,
                    0.2,
                    0.2,
                    0.2
                ]
            ]
        },
        {
            "name": "obelisk_inactive",
            "delays": [
                [
                    0.6,
                    0.6
                ]
            ]
        },
        {
            "name": "obelisk_unwrenched"
        },
        {
            "name": "obelisk_prism",
            "delays": [
                [
                    3,
                    0.2,
                    0.2,
                    0.2,
                    0.2,
                    0.2,
                    0.2,
                    0.2,
                    0.2,
                    0.2,
                    0.2,
                    0.2,
                    0.2,
                    0.2,
                    0.2,
                    0.2,
                    0.2,
                    0.2,
                    0.2,
                    0.2,
                    0.2,
                    0.2
                ]
            ]
        },
        {
            "name": "stargazer"
        },
        {
            "name": "stargazer_unwrenched"
        },
        {
            "name": "stargazer_light"
        },
        {
            "name": "brass_skewer"
        },
        {
            "name": "brass_skewer_extended"
        },
        {
            "name": "brass_skewer_pokeybit"
        },
        {
            "name": "steam_vent_0"
        },
        {
            "name": "steam_vent_1",
            "delays": [
                [
                    0.1,
                    0.1
                ]
            ]
        },
        {
            "name": "flipper",
            "directions": 4,
            "delays": [
                [
                    0.02,
                    0.02,
                    0.02,
                    0.02,
                    0.02,
                    0.1,
                    0.1,
                    0.1
                ],
                [
                    0.02,
                    0.02,
                    0.02,
                    0.02,
                    0.02,
                    0.1,
                    0.1,
                    0.1
                ],
                [
                    0.02,
                    0.02,
                    0.02,
                    0.02,
                    0.02,
                    0.1,
                    0.1,
                    0.1
                ],
                [
                    0.02,
                    0.02,
                    0.02,
                    0.02,
                    0.02,
                    0.1,
                    0.1,
                    0.1
                ]
            ]
        },
        {
            "name": "pressure_sensor"
        },
        {
            "name": "lever"
        },
        {
            "name": "repeater"
        },
        {
            "name": "repeater_on",
            "delays": [
                [
                    0.1,
                    0.1,
                    0.1
                ]
            ]
        },
        {
            "name": "delayer_active",
            "delays": [
                [
                    0.1,
                    0.1,
                    0.1,
                    0.1,
                    0.1
                ]
            ]
        },
        {
            "name": "delayer"
        },
        {
            "name": "clockwork_floor"
        },
        {
            "name": "clockwork_wall"
        },
        {
            "name": "wall_gear"
        },
        {
            "name": "marauder_armor"
        },
        {
            "name": "fallen_armor"
        },
        {
            "name": "anime_fragment"
        },
        {
            "name": "smashed_anime_fragment",
            "delays": [
                [
                    4.9,
                    2.1,
                    4.9,
                    2.1
                ]
            ]
        },
        {
            "name": "cogscarab_shell"
        },
        {
            "name": "alloy_shards",
            "delays": [
                [
                    5,
                    0.2,
                    0.060000002,
                    4,
                    0.14,
                    0.2,
                    0.2,
                    0.2,
                    0.2,
                    0.2,
                    0.2,
                    0.2,
                    0.2,
                    0.2,
                    0.2,
                    0.2,
                    0.2
                ]
            ]
        },
        {
            "name": "pinion_lock"
        },
        {
            "name": "shard_small1",
            "delays": [
                [
                    5,
                    0.2,
                    0.060000002,
                    4,
                    0.14,
                    0.2,
                    0.2,
                    0.2,
                    0.2,
                    0.2,
                    0.2,
                    0.2,
                    0.2,
                    0.2,
                    0.2,
                    0.2,
                    0.2
                ]
            ]
        },
        {
            "name": "shard_small2",
            "delays": [
                [
                    5,
                    0.2,
                    0.060000002,
                    4,
                    0.14,
                    0.2,
                    0.2,
                    0.2,
                    0.2,
                    0.2,
                    0.2,
                    0.2,
                    0.2,
                    0.2,
                    0.2,
                    0.2,
                    0.2
                ]
            ]
        },
        {
            "name": "shard_small3",
            "delays": [
                [
                    5,
                    0.2,
                    0.060000002,
                    4,
                    0.14,
                    0.2,
                    0.2,
                    0.2,
                    0.2,
                    0.2,
                    0.2,
                    0.2,
                    0.2,
                    0.2,
                    0.2,
                    0.2,
                    0.2
                ]
            ]
        },
        {
            "name": "shard_medium1",
            "delays": [
                [
                    5,
                    0.2,
                    0.060000002,
                    4,
                    0.14,
                    0.2,
                    0.2,
                    0.2,
                    0.2,
                    0.2,
                    0.2,
                    0.2,
                    0.2,
                    0.2,
                    0.2,
                    0.2,
                    0.2
                ]
            ]
        },
        {
            "name": "shard_medium2",
            "delays": [
                [
                    5,
                    0.2,
                    0.060000002,
                    4,
                    0.14,
                    0.2,
                    0.2,
                    0.2,
                    0.2,
                    0.2,
                    0.2,
                    0.2,
                    0.2,
                    0.2,
                    0.2,
                    0.2,
                    0.2
                ]
            ]
        },
        {
            "name": "shard_large1",
            "delays": [
                [
                    5,
                    0.2,
                    0.060000002,
                    4,
                    0.14,
                    0.2,
                    0.2,
                    0.2,
                    0.2,
                    0.2,
                    0.2,
                    0.2,
                    0.2,
                    0.2,
                    0.2,
                    0.2,
                    0.2
                ]
            ]
        },
        {
            "name": "shard_large2",
            "delays": [
                [
                    5,
                    0.2,
                    0.060000002,
                    4,
                    0.14,
                    0.2,
                    0.2,
                    0.2,
                    0.2,
                    0.2,
                    0.2,
                    0.2,
                    0.2,
                    0.2,
                    0.2,
                    0.2,
                    0.2
                ]
            ]
        },
        {
            "name": "clockgolem_dead"
        },
        {
            "name": "gear_bit1"
        },
        {
            "name": "gear_bit2"
        },
        {
            "name": "gear_bit3"
        },
        {
            "name": "gear_bit4"
        },
        {
            "name": "relay",
            "delays": [
                [
                    0.05,
                    0.05,
                    0.05,
                    0.05,
                    0.05,
                    0.05,
                    0.05,
                    0.05,
                    0.05,
                    0.05,
                    0.05,
                    0.05,
                    0.05,
                    0.05,
                    0.05,
                    0.05,
                    0.05,
                    0.05,
                    0.05,
                    0.05,
                    0.05,
                    0.05,
                    0.05,
                    0.05,
                    0.05,
                    0.05,
                    1.4
                ]
            ]
        },
        {
            "name": "relay_off"
        },
        {
            "name": "relay_o"
        },
        {
            "name": "integration_cog"
        },
        {
            "name": "stargazer_closed"
        },
        {
            "name": "stargazer_opening",
            "delays": [
                [
                    0.1,
                    0.1,
                    0.1
                ]
            ]
        },
        {
            "name": "stargazer_closing",
            "delays": [
                [
                    0.1,
                    0.1,
                    0.1
                ]
            ]
        },
        {
            "name": "gear_base_unwrenched"
        },
        {
            "name": "ratvarian_hammer",
            "delays": [
                [
                    1,
                    0.1,
                    0.1,
                    0.1,
                    0.1,
                    0.1,
                    0.1,
                    0.1,
                    0.1,
                    0.1
                ]
            ]
        },
        {
            "name": "ratvarian_sword"
        }
    ]
}
